odoo/addons/partner_subject_to_vat/README.rst
odoo/addons/partner_subject_to_vat/__init__.py
odoo/addons/partner_subject_to_vat/__manifest__.py
odoo/addons/partner_subject_to_vat/i18n/it.po
odoo/addons/partner_subject_to_vat/i18n/partner_subject_to_vat.pot
odoo/addons/partner_subject_to_vat/models/__init__.py
odoo/addons/partner_subject_to_vat/models/res_partner.py
odoo/addons/partner_subject_to_vat/readme/CONTRIBUTORS.rst
odoo/addons/partner_subject_to_vat/readme/DESCRIPTION.rst
odoo/addons/partner_subject_to_vat/static/description/icon.png
odoo/addons/partner_subject_to_vat/static/description/index.html
odoo/addons/partner_subject_to_vat/views/res_partner_view.xml
odoo_addon_partner_subject_to_vat-16.0.1.0.0.4.dist-info/METADATA
odoo_addon_partner_subject_to_vat-16.0.1.0.0.4.dist-info/WHEEL
odoo_addon_partner_subject_to_vat-16.0.1.0.0.4.dist-info/top_level.txt
odoo_addon_partner_subject_to_vat-16.0.1.0.0.4.dist-info/RECORD
